pylaser/__init__.py
pylaser-0.1.1.dist-info/METADATA
pylaser-0.1.1.dist-info/WHEEL
pylaser-0.1.1.dist-info/top_level.txt
pylaser-0.1.1.dist-info/RECORD
